memorize/__init__.py
memorize/memorize.py
memorize.py-1.2.dist-info/METADATA
memorize.py-1.2.dist-info/RECORD
memorize.py-1.2.dist-info/WHEEL
memorize.py-1.2.dist-info/top_level.txt
