Metadata-Version: 1.0
Name: memorize.py
Version: 1.2
Summary: Simple decorator for memoizing a function across multiple program executions.
Home-page: https://github.com/brmscheiner/memorize.py
Author: Ben Scheiner
Author-email: UNKNOWN
License: UNKNOWN
Keywords: memorize memoize pickle
Platform: UNKNOWN
